neidspec/CreateTemplate.py
neidspec/__init__.py
neidspec/bary.py
neidspec/lines.py
neidspec/neidspec.py
neidspec/priors.py
neidspec/rotbroad_help.py
neidspec/rv_utils.py
neidspec/spec_help.py
neidspec/stats_help.py
neidspec/target.py
neidspec/utils.py
neidspec/version.py
neidspec/data/masks/ccf/20190730_gj699_combined_stellarframe_mod_k225b.mas
neidspec/data/masks/ccf/gj699.mas
neidspec/data/masks/ccf/gj699_combined_stellarframe.mas
neidspec/data/masks/ccf/specmatch_mask.mas
neidspec/data/masks/sky/HPF_SkyEmmissionLineWavlMask_broadened_11111_Compressed.txt
neidspec/data/masks/telluric/20240221_tellneid_conv21_thres0.995_r115000.dat
neidspec/data/masks/telluric/telfit_telmask_conv17_thres0.995_with17area.dat
neidspec/data/neidmasterfile/neidMaster_InstrumentResponse_HR_20221111_v1.fits
neidspec/data/target_files/GJ_699.config
neidspec/data/target_files/G_227-22.config
neidspec/data/target_files/HD 86728.config
neidspec-0.1.0.dist-info/METADATA
neidspec-0.1.0.dist-info/WHEEL
neidspec-0.1.0.dist-info/top_level.txt
neidspec-0.1.0.dist-info/RECORD
